{
	"format_version": "1.8.0",
	"animations": {
		"swim_idle": {
			"loop": true,
			"animation_length": 2.08,
			"bones": {
				"body": {
					"position": {
						"0.0": {
							"vector": [0, 0, 0]
						},
						"1.04": {
							"vector": [0, 2, 0]
						},
						"2.08": {
							"vector": [0, 0, 0]
						}
					}
				},
				"right_arm": {
					"rotation": {
						"0.0": {
							"vector": [-90, 17.5, 0]
						},
						"1.04": {
							"vector": [20.25035, -14.18684, 77.23977]
						},
						"1.56": {
							"vector": [-8.41432, 38.43314, 108.73322]
						},
						"2.08": {
							"vector": [-90, 17.5, 0]
						}
					}
				},
				"left_arm": {
					"rotation": {
						"0.0": {
							"vector": [-90, -17.5, 0]
						},
						"1.04": {
							"vector": [19.72799, 11.8575, -78.10937]
						},
						"1.56": {
							"vector": [-14.87756, -37.04749, -97.45388]
						},
						"2.08": {
							"vector": [-90, -17.5, 0]
						}
					}
				},
				"right_leg": {
					"rotation": {
						"0.0": {
							"vector": [-45, 0, 0]
						},
						"0.52": {
							"vector": [41, 0, 0]
						},
						"1.04": {
							"vector": [-45, 0, 0]
						},
						"1.56": {
							"vector": [41, 0, 0]
						},
						"2.08": {
							"vector": [-45, 0, 0]
						}
					}
				},
				"left_leg": {
					"rotation": {
						"0.0": {
							"vector": [40, 0, 0]
						},
						"0.52": {
							"vector": [-42.5, 0, 0]
						},
						"1.04": {
							"vector": [40, 0, 0]
						},
						"1.56": {
							"vector": [-42.5, 0, 0]
						},
						"2.08": {
							"vector": [40, 0, 0]
						}
					}
				}
			}
		}
	},
	"geckolib_format_version": 2
}